debt_optimizer/__init__.py
debt_optimizer/__version__.py
debt_optimizer/cli/__init__.py
debt_optimizer/cli/commands.py
debt_optimizer/core/__init__.py
debt_optimizer/core/balance_updater.py
debt_optimizer/core/config.py
debt_optimizer/core/debt_optimizer.py
debt_optimizer/core/financial_calc.py
debt_optimizer/core/logging_config.py
debt_optimizer/core/validation.py
debt_optimizer/excel_io/__init__.py
debt_optimizer/excel_io/excel_reader.py
debt_optimizer/excel_io/excel_writer.py
debt_optimizer/visualization/__init__.py
debt_optimizer/visualization/charts.py
financial_debt_optimizer-2.0.1.dist-info/licenses/LICENSE
tests/__init__.py
tests/conftest.py
tests/test_cli_commands.py
tests/test_config.py
tests/test_debt_optimizer.py
tests/test_excel_io.py
tests/test_financial_calc.py
tests/test_integration.py
tests/test_logging_config.py
tests/test_validation.py
tests/test_version.py
tests/test_visualization.py
financial_debt_optimizer-2.0.1.dist-info/METADATA
financial_debt_optimizer-2.0.1.dist-info/WHEEL
financial_debt_optimizer-2.0.1.dist-info/entry_points.txt
financial_debt_optimizer-2.0.1.dist-info/top_level.txt
financial_debt_optimizer-2.0.1.dist-info/RECORD
