Metadata-Version: 2.4
Name: financial-debt_optimizer
Version: 2.0.1
Summary: A comprehensive tool for analyzing and optimizing debt repayment strategies
Home-page: https://github.com/bryankemp/financial-debt_optimizer
Author: Bryan Kemp
Author-email: bryan@kempville.com
Project-URL: Bug Reports, https://github.com/bryankemp/financial-debt_optimizer/issues
Project-URL: Source, https://github.com/bryankemp/financial-debt_optimizer
Project-URL: Documentation, https://github.com/bryankemp/financial-debt_optimizer#readme
Keywords: debt optimization finance calculator repayment strategy
Classifier: Development Status :: 5 - Production/Stable
Classifier: Intended Audience :: End Users/Desktop
Classifier: Intended Audience :: Financial and Insurance Industry
Classifier: License :: OSI Approved :: BSD License
Classifier: Operating System :: OS Independent
Classifier: Programming Language :: Python :: 3
Classifier: Programming Language :: Python :: 3.8
Classifier: Programming Language :: Python :: 3.9
Classifier: Programming Language :: Python :: 3.10
Classifier: Programming Language :: Python :: 3.11
Classifier: Programming Language :: Python :: 3.12
Classifier: Topic :: Office/Business :: Financial
Classifier: Topic :: Office/Business :: Financial :: Accounting
Classifier: Topic :: Scientific/Engineering :: Mathematics
Requires-Python: >=3.8
License-File: LICENSE
Requires-Dist: pandas
Requires-Dist: numpy
Requires-Dist: xlsxwriter
Requires-Dist: openpyxl
Requires-Dist: click
Requires-Dist: matplotlib
Requires-Dist: pyyaml
Provides-Extra: dev
Requires-Dist: pytest>=6.2.5; extra == "dev"
Requires-Dist: black>=21.5b2; extra == "dev"
Requires-Dist: pylint>=2.8.2; extra == "dev"
Requires-Dist: mypy>=0.910; extra == "dev"
Provides-Extra: test
Requires-Dist: pytest>=6.2.5; extra == "test"
Requires-Dist: pytest-cov>=2.12.0; extra == "test"
Provides-Extra: balance
Requires-Dist: rapidfuzz>=3.0.0; extra == "balance"
Dynamic: author
Dynamic: author-email
Dynamic: classifier
Dynamic: description
Dynamic: description-content-type
Dynamic: home-page
Dynamic: keywords
Dynamic: license-file
Dynamic: project-url
Dynamic: provides-extra
Dynamic: requires-dist
Dynamic: requires-python
Dynamic: summary
